naver_search_ad/__init__.py
naver_search_ad/common.py
naver_search_ad/keywords.py
naver_search_ad-1.5.dist-info/METADATA
naver_search_ad-1.5.dist-info/WHEEL
naver_search_ad-1.5.dist-info/top_level.txt
naver_search_ad-1.5.dist-info/RECORD
